pytable_formatter/__init__.py
pytable_formatter/cell.py
pytable_formatter/enums.py
pytable_formatter/table.py
pytable_formatter/utils.py
pytable_formatter-0.1.1.dist-info/LICENSE
pytable_formatter-0.1.1.dist-info/METADATA
pytable_formatter-0.1.1.dist-info/WHEEL
pytable_formatter-0.1.1.dist-info/top_level.txt
pytable_formatter-0.1.1.dist-info/RECORD
