Metadata-Version: 2.2
Name: pytable-formatter
Version: 0.1.1
Summary: Advanced table formatting for terminal output
Home-page: https://github.com/biswanathroul/pytable-formatter
Author: Biswanath Roul
Project-URL: Bug Tracker, https://github.com/biswanathroul/pytable-formatter/issues
Keywords: table,terminal,cli,formatting,console
Classifier: Programming Language :: Python :: 3
Classifier: Programming Language :: Python :: 3.6
Classifier: Programming Language :: Python :: 3.7
Classifier: Programming Language :: Python :: 3.8
Classifier: Programming Language :: Python :: 3.9
Classifier: License :: OSI Approved :: MIT License
Classifier: Operating System :: OS Independent
Classifier: Environment :: Console
Classifier: Intended Audience :: Developers
Classifier: Topic :: Software Development :: Libraries :: Python Modules
Classifier: Topic :: Utilities
Requires-Python: >=3.6
License-File: LICENSE
Dynamic: author
Dynamic: classifier
Dynamic: description
Dynamic: description-content-type
Dynamic: home-page
Dynamic: keywords
Dynamic: project-url
Dynamic: requires-python
Dynamic: summary
